{
  "RegEx": {
    "site": "https://regex101.com/",
    "name": "Potion of Cure Light Wounds (cr, 50 gp)",
    "item name": "/Potion of ([\\w+\\s]+)/gm",
    "item gp": "/\\d+\\s[pp|gp|sp|cp]/gm",
    "item weight": "/\\d+\\slb/gm"
  },


  "class_ages": {
    "Intuitive": [ "barbarians", "oracles", "rogues", "sorcerers" ],
    "Self-Taught": [ "bards", "cavaliers", "fighters", "gunslingers", "paladins", "rangers", "summoners", "witches" ],
    "Trained": [ "alchemists", "clerics", "druids", "inquisitors", "magi", "monks", "wizards" ]
  },
  "player_wealth": [ 0, 111, 1000, 3000, 6000 , 10500 , 16000 , 23500, 33000, 46000, 62000, 82000, 108000, 140000, 185000, 240000, 315000, 410000, 530000, 685000, 880000 ],
  "heroic_wealth": [ 0, 390, 780, 1650, 2400, 3450, 4650, 6000, 7800, 10050, 12750, 16350, 21000, 27000, 34800, 45000, 58500, 75000, 96000, 123000, 159000 ],
  "basic_wealth": [ 0, 260, 390, 780, 1650, 2400, 3450, 4650, 6000, 7800, 10050, 12750, 16350, 21000, 27000, 34800, 45000, 58500, 75000, 96000, 123000 ],
  "damage_types": {
    "weapon":     [ "budgeoning", "piercing", "slashing" ],
    "energy":     [ "acid", "cold", "electricity", "fire", "force", "negative", "positive", "sonic" ],
    "aligned":    [ "chaoic", "evil", "good", "lawful" ],
    "substance":  [ "adamantine", "cold Iron", "epic", "magic", "silver" ],
    "misc":       [ "bleed", "nonlethal", "precision", "spell", "untyped" ]
  },

  "natural_attacks": {
    "Bite": {
      "Damage": {  "fine": "1",  "diminuitive": "1d2",  "tiny": "1d3",  "small": "1d4",  "medium": "1d6",  "large": "1d8",  "huge": "2d6",  "gargantuan": "2d8",  "colossal": "4d6"  },
      "Critical": "20/x2",
      "Range": 0,
      "Damage Type": [ "Bludgeoning", "Piercing", "Slashing" ],
      "Proficiency": "Natural",
      "Category": "Primary"
    },
    "Claw": {
      "Damage": {  "fine": "0",  "diminuitive": "1",  "tiny": "1d2",  "small": "1d3",  "medium": "1d4",  "large": "1d6",  "huge": "1d8",  "gargantuan": "2d6",  "colossal": "2d8"  },
      "Critical": "20/x2",
      "Range": 0,
      "Damage Type": [ "Bludgeoning", "Slashing" ],
      "Proficiency": "Natural",
      "Category": "Primary"
    },
    "Gore": {
      "Damage": {  "fine": "0",  "diminuitive": "1d2",  "tiny": "1d3",  "small": "1d4",  "medium": "1d6",  "large": "1d8",  "huge": "2d6",  "gargantuan": "2d8",  "colossal": "4d6"  },
      "Critical": "20/x2",
      "Range": 0,
      "Damage Type": [ "Piercing" ],
      "Proficiency": "Natural",
      "Category": "Primary"
    },
    "Hoof": {
      "Damage": {  "fine": "0",  "diminuitive": "1",  "tiny": "1d2",  "small": "1d3",  "medium": "1d4",  "large": "1d5",  "huge": "1d8",  "gargantuan": "2d6",  "colossal": "2d8"  },
      "Critical": "20/x2",
      "Range": 0,
      "Damage Type": [ "Bludgeoning" ],
      "Proficiency": "Natural",
      "Category": "Secondary"
    },
    "Tentacle": {
      "Damage": {  "fine": "0",  "diminuitive": "1",  "tiny": "1d2",  "small": "1d3",  "medium": "1d4",  "large": "1d5",  "huge": "1d8",  "gargantuan": "2d6",  "colossal": "2d8"  },
      "Critical": "20/x2",
      "Range": 0,
      "Damage Type": [ "Bludgeoning" ],
      "Proficiency": "Natural",
      "Category": "Secondary"
    },
    "Wing": {
      "Damage": {  "fine": "0",  "diminuitive": "1",  "tiny": "1d2",  "small": "1d3",  "medium": "1d4",  "large": "1d6",  "huge": "1d8",  "gargantuan": "2d6",  "colossal": "2d8"  },
      "Critical": "20/x2",
      "Range": 0,
      "Damage Type": [ "Bludgeoning" ],
      "Proficiency": "Natural",
      "Category": "Secondary"
    },
    "Pincers": {
      "Damage": {  "fine": "1",  "diminuitive": "1d2",  "tiny": "1d3",  "small": "1d4",  "medium": "1d6",  "large": "1d8",  "huge": "2d6",  "gargantuan": "2d8",  "colossal": "4d6"  },
      "Critical": "20/x2",
      "Range": 0,
      "Damage Type": [ "Bludgeoning" ],
      "Proficiency": "Natural",
      "Category": "Secondary"
    },
    "Tail Slap": {
      "Damage": {  "fine": "1",  "diminuitive": "1d2",  "tiny": "1d3",  "small": "1d4",  "medium": "1d6",  "large": "1d8",  "huge": "2d6",  "gargantuan": "2d8",  "colossal": "4d6"  },
      "Critical": "20/x2",
      "Range": 0,
      "Damage Type": [ "Bludgeoning" ],
      "Proficiency": "Natural",
      "Category": "Secondary"
    },
    "Slam": {
      "Damage": {  "fine": "0",  "diminuitive": "1",  "tiny": "1d2",  "small": "1d3",  "medium": "1d4",  "large": "1d6",  "huge": "1d8",  "gargantuan": "2d6",  "colossal": "2d8"  },
      "Critical": "20/x2",
      "Range": 0,
      "Damage Type": [ "Bludgeoning" ],
      "Proficiency": "Natural",
      "Category": "Primary"
    },
    "Sting": {
      "Damage": {  "fine": "0",  "diminuitive": "1",  "tiny": "1d2",  "small": "1d3",  "medium": "1d4",  "large": "1d6",  "huge": "1d8",  "gargantuan": "2d6",  "colossal": "2d8"  },
      "Critical": "20/x2",
      "Range": 0,
      "Damage Type": [ "Piercing" ],
      "Proficiency": "Natural",
      "Category": "Primary"
    },
    "Talons": {
      "Damage": {  "fine": "0",  "diminuitive": "1",  "tiny": "1d2",  "small": "1d3",  "medium": "1d4",  "large": "1d6",  "huge": "1d8",  "gargantuan": "2d6",  "colossal": "2d8"  },
      "Critical": "20/x2",
      "Range": 0,
      "Damage Type": [ "Slashing" ],
      "Proficiency": "Natural",
      "Category": "Primary"
    },
    "Other": {
      "Damage": {  "fine": "0",  "diminuitive": "1",  "tiny": "1d2",  "small": "1d3",  "medium": "1d4",  "large": "1d6",  "huge": "1d8",  "gargantuan": "2d6",  "colossal": "2d8"  },
      "Critical": "20/x2",
      "Range": 0,
      "Damage Type": [ "Bludgeoning", "Piercing", "Slashing" ],
      "Proficiency": "Natural",
      "Category": "Secondary"
    }
  },

  "size": {
    "fine": {
      "ac / atk":   8,
      "cmb / cmd": -8,
      "flight":     8,
      "stealth":    16,
      "carry mod":  0.125,
      "extra legs": 0.25,

      "space":      "1/2 ft.",
      "reach tall": "0 ft.",
      "reach long": "0 ft.",
      "dimensions": "6 inches or less",
      "weight":     "1/8 lb. or less"
    },
    "diminuitive": {
      "ac / atk":   4,
      "cmb / cmd": -4,
      "flight":     6,
      "stealth":    12,
      "carry mod":  0.25,
      "extra legs": 0.5,

      "space":      "1 ft.",
      "reach tall": "0 ft.",
      "reach long": "0 ft.",
      "dimensions": "6 in. - 1 ft.",
      "weight":     "1/8 lb. - 1 lb."
    },
    "tiny": {
      "ac / atk":   2,
      "cmb / cmd":  -2,
      "flight":     4,
      "stealth":    8,
      "carry mod":  0.5,
      "extra legs": 0.75,

      "space":      "2 - 2.5 ft.",
      "reach tall": "0 ft.",
      "reach long": "0 ft.",
      "dimensions": "1 - 2 ft.",
      "weight":     "1 - 8 lbs."
    },
    "small": {
      "ac / atk":   1,
      "cmb / cmd":  -1,
      "flight":     2,
      "stealth":    4,
      "carry mod":  0.5,
      "extra legs": 1,

      "space":      "5 ft.",
      "reach tall": "5 ft.",
      "reach long": "5 ft.",
      "dimensions": "2 - 4 ft.",
      "weight":     "8 - 60 lbs."
    },
    "medium": {
      "ac / atk":   0,
      "cmb / cmd":  0,
      "flight":     0,
      "stealth":    0,
      "carry mod":  1,
      "extra legs": 1.5,

      "space":      "5 ft.",
      "reach tall": "5 ft.",
      "reach long": "5 ft.",
      "dimensions": "4 - 8 ft.",
      "weight":     "60 - 500 lbs."
    },
    "large": {
      "ac / atk":   -1,
      "cmb / cmd":  1,
      "flight":     -2,
      "stealth":    -4,
      "carry mod":  2,
      "extra legs": 3,

      "space":      "10 ft.",
      "reach tall": "10 ft.",
      "reach long": "5 ft.",
      "dimensions": "8 - 16 ft.",
      "weight":     "500 - 4000 lbs."
    },
    "huge": {
      "ac / atk":   -2,
      "cmb / cmd":  2,
      "flight":     -4,
      "stealth":    -8,
      "carry mod":  4,
      "extra legs": 6,

      "space":      "15 ft.",
      "reach tall": "15 ft.",
      "reach long": "10 ft.",
      "dimensions": "16 - 32 ft.",
      "weight":     "2 - 16 tons"
    },
    "gargantuan": {
      "ac / atk":   -4,
      "cmb / cmd":  4,
      "flight":     -6,
      "stealth":    -12,
      "carry mod":  8,
      "extra legs": 12,

      "space":      "20 ft.",
      "reach tall": "20 ft.",
      "reach long": "15 ft.",
      "dimensions": "32 - 64 ft.",
      "weight":     "16 - 125 tons"
    },
    "colossal": {
      "ac / atk":   -8,
      "cmb / cmd":  8,
      "flight":     -8,
      "stealth":    -16,
      "carry mod":  16,
      "extra legs": 24,

      "space":      "30 ft.",
      "reach tall": "30 ft.",
      "reach long": "20 ft.",
      "dimensions": "64 ft. or more",
      "weight":     "125 tons or more"
    }
  },

  "bonuses": {
    "Alchemical": {
      "description": "An alchemical bonus is granted by the use of a non-magical, alchemical substance such as antitoxin.",
      "targets": [ "Ability Scores", "Saves" ],
      "subtargets": [ "fort", "ref", "will" ]
    },
    "Armor": {
      "description": "An armor bonus applies to armor class and is granted by armor or by a spell or magical effect that mimics armor. Armor bonuses stack with all other bonuses to armor class (even with natural armor bonuses) except other armor bonuses. An armor bonus doesn’t apply against touch attacks, except for armor bonuses granted by force effects (such as the mage armor spell) which apply against incorporeal touch attacks, such as that of a shadow.",
      "targets": [ "totalAC", "flatAC" ],
      "subtargets": [ "flat" ]
    },
    "Circumstance": {
      "description": "A circumstance bonus (or penalty) arises from specific conditional factors impacting the success of the task at hand. Circumstance bonuses stack with all other bonuses, including other circumstance bonuses, unless they arise from essentially the same source.",
      "targets": [ "atkBonus", "Checks" ]
    },
    "Competence": {
      "description": "A competence bonus (or penalty) affects a character’s performance of a particular task, as in the case of the bardic ability to inspire competence. Multiple competence bonuses don’t stack; only the highest bonus applies.",
      "targets": [ "atkBonus", "Checks", "Saves" ],
      "subtargets": [ "fort", "ref", "will" ]
    },
    "Deflection": {
      "description": "A deflection bonus affects armor class and is granted by a spell or magic effect that makes attacks veer off harmlessly. Deflection bonuses stack with all other bonuses to AC except other deflection bonuses. A deflection bonus applies against touch attacks.",
      "targets": [ "totalAC", "touchAC", "flatAC" ],
      "subtargets": [ "touch", "flat" ]
    },
    "Enhancement": {
      "description": "An enhancement bonus represents an increase in the effectiveness of armor, natural armor, weapon, or a general bonus to an ability score. Multiple enhancement bonuses on the same object (in the case of armor and weapons), creature (in the case of natural armor), or ability score do not stack. Only the highest enhancement bonus applies.",
      "targets": [ "Ability Scores", "totalAC", "touchAC", "flatAC", "atkBonus", "dmgBonus", "Speed" ],
      "subtargets": [ "touch", "flat", "fort", "ref", "will" ]
    },
    "Insight": {
      "description": "An insight bonus improves performance of a given activity by granting the character an almost precognitive knowledge of what might occur. Multiple insight bonuses on the same character or object do not stack. Only the highest insight bonus applies.",
      "targets": [ "totalAC", "touchAC", "flatAC", "atkBonus", "Checks", "Saves" ],
      "subtargets": [ "touch", "flat", "fort", "ref", "will" ]
    },
    "Luck": {
      "description": "A luck bonus represents good (or bad) fortune. Multiple luck bonuses on the same character or object do not stack. Only the highest luck bonus applies.",
      "targets": [ "totalAC", "touchAC", "flatAC", "atkBonus", "Checks", "dmgBonus", "Saves" ],
      "subtargets": [ "touch", "flat", "fort", "ref", "will" ]
    },
    "Morale": {
      "description": "A morale bonus represents the effects of greater hope, courage, and determination (or hopelessness, cowardice, and despair in the case of a morale penalty). Multiple morale bonuses on the same character do not stack. Only the highest morale bonus applies. Non-intelligent creatures (creatures with an Intelligence of 0 or no Intelligence at all) cannot benefit from morale bonuses.",
      "targets": [  "atkBonus", "Checks", "dmgBonus", "Saves", "Str", "Con", "Dex" ],
      "subtargets": [ "fort", "ref", "will" ]
    },
    "Natural Armor": {
      "description": "A natural armor bonus improves armor class resulting from a creature’s naturally tough hide. Natural armor bonuses stack with all other bonuses to armor class (even with armor bonuses) except other natural armor bonuses. Some magical effects (such as the barkskin spell) grant an enhancement bonus to the creature’s existing natural armor bonus, which has the effect of increasing the natural armor’s overall bonus to armor class. A natural armor bonus doesn’t apply against touch attacks.",
      "targets": [ "totalAC", "flatAC" ],
      "subtargets": [ "flat" ]
    },
    "Profane": {
      "description": "A profane bonus (or penalty) stems from the power of evil. Multiple profane bonuses on the same character or object do not stack. Only the highest profane bonus applies.",
      "targets": [  "totalAC", "touchAC", "flatAC", "Checks", "dmgBonus", "DCs", "Saves" ],
      "subtargets": [ "touch", "flat", "fort", "ref", "will" ]
    },
    "Resistance": {
      "description": "A resistance bonus affects saving throws, providing extra protection against harm. Multiple resistance bonuses on the same character or object do not stack. Only the highest resistance bonus applies.",
      "targets": [ "Saves" ],
      "subtargets": [ "fort", "ref", "will" ]
    },
    "Sacred": {
      "description": "A sacred bonus (or penalty) stems from the power of good. Multiple sacred bonuses on the same character or object do not stack. Only the highest sacred bonus applies.",
      "targets": [ "totalAC", "touchAC", "flatAC", "Checks", "dmgBonus", "DCs", "Saves" ],
      "subtargets": [ "touch", "flat", "fort", "ref", "will" ]
    },
    "Shield": {
      "description": "A shield bonus improves armor class and is granted by a shield or by a spell or magic effect that mimics a shield. Shield bonuses stack with all other bonuses to AC except other shield bonuses. A magic shield typically grants an enhancement bonus to the shield’s shield bonus, which has the effect of increasing the shield’s overall bonus to AC.",
      "targets": [ "totalAC", "flatAC" ],
      "subtargets": [ "flat" ]
    },
    "Size": {
      "description": "A size bonus or penalty is derived from a creature’s size category. Size modifiers of different kinds apply to armor class, attack rolls, Stealth checks, combat maneuver checks, and various other checks.",
      "targets": [ "Ability Scores", "atkBonus", "totalAC", "touchAC", "flatAC" ],
      "subtargets": [ "touch", "flat" ]
    },
    "Trait": {
      "description": "A trait bonus is a bonus granted via a character trait. Character traits are an optional additional character defining feature like feats but less powerful (typically about half as strong as a feat.) As with other named bonuses, trait bonuses do not “stack” with other trait bonuses.",
      "targets": []
    }
  },

  "creature_types": {
    "aberration": {
      "hd": 8,
      "ranks": 4,
      "bab": 0.75,
      "fort": { "mult": 0.33, "bonus": 0 },
      "ref": { "mult": 0.33, "bonus": 0 },
      "will": { "mult": 0.5, "bonus": 2 },
      "skills": [ "Acrobatics", "Climb", "Escape Artist", "Fly", "Intimidate", "Perception", "Spellcraft", "Stealth", "Survival", "Swim" ],
      "traits": {
        "Darkvision": {
          "trigger": "Continuous",
          "descripction": "Aberrations can see in the dark up to 60 feet.",
          "benefit": { "target": "senses", "text": "Darkvision 60 ft." },
          "bonuses": {}
        }
      }
    },
    "animal": {
      "hd": 8,
      "ranks": 2,
      "bab": 0.75,
      "fort": { "mult": 0.5, "bonus": 2 },
      "ref": { "mult": 0.5, "bonus": 2 },
      "will": { "mult": 0.33, "bonus": 0 },
      "skills": [ "Acrobatics", "Climb", "Fly", "Perception", "Stealth", "Swim" ],
      "traits": {
        "Low-light Vision": {
          "trigger": "Continuous",
          "descripction": "Animals can see color in dim light.",
          "benefit": { "target": "senses", "text": "Low-Light Vision" },
          "bonuses": {}
        }
      }
    },
    "construct": {
      "hd": 10,
      "ranks": 2,
      "bab": 1,
      "fort": { "mult": 0.33, "bonus": 0 },
      "ref": { "mult": 0.33, "bonus": 0 },
      "will": { "mult": 0.33, "bonus": 0 },
      "skills": [],
      "traits": {
        "Darkvision": {
          "trigger": "Continuous",
          "descripction": "Constructs can see in the dark up to 60 feet.",
          "benefit": { "target": "senses", "text": "Darkvision 60 ft." },
          "bonuses": {}
        },
        "Low-light Vision": {
          "trigger": "Continuous",
          "descripction": "Constructs can see color in dim light.",
          "benefit": { "target": "senses", "text": "Low-Light Vision" },
          "bonuses": {}
        },
        "Construct Immunities": {
          "trigger": "Continuous",
          "descripction": "Constructs is a magically animated or artificially created creatures, granting them a number of immunities.",
          "benefit": { "target": "immunities", "text":
            "nonlethal damage, necromancy, fatigue, exhaustion, stunning, paralysis, sleep, poison, mind effects, disease, ability damage, death effects, ability drain, energy drain"
          },
          "bonuses": {}
        }
      }
    },
    "dragon": {
      "hd": 12,
      "ranks": 6,
      "bab": 1,
      "fort": { "mult": 0.5, "bonus": 2 },
      "ref": { "mult": 0.5, "bonus": 2 },
      "will": { "mult": 0.5, "bonus": 2 },
      "skills": [ "Appraise", "Bluff", "Climb", "Craft", "Diplomacy", "Fly", "Heal", "Intimidate", "Knowledge (arcana)", "Knowledge (dungeoneering)", "Knowledge (engineering)", "Knowledge (geography)", "Knowledge (history)", "Knowledge (local)", "Knowledge (nature)", "Knowledge (nobility)", "Knowledge (planes)", "Knowledge (religion)", "Linguistics", "Perception", "Sense Motive", "Spellcraft", "Stealth", "Survival", "Swim", "Use Magic Device" ],
      "traits": {
        "Darkvision": {
          "trigger": "Continuous",
          "descripction": "Dragons can see in the dark up to 60 feet.",
          "benefit": { "target": "senses", "text": "Darkvision 60 ft." },
          "bonuses": {}
        },
        "Low-light Vision": {
          "trigger": "Continuous",
          "descripction": "Dragons can see color in dim light.",
          "benefit": { "target": "senses", "text": "Low-Light Vision" },
          "bonuses": {}
        },
        "Dragon Immunities": {
          "trigger": "Continuous",
          "descripction": "Dragons are immune to magical sleep and paralysis.",
          "benefit": { "target": "immunities", "text": "paralysis, sleep" },
          "bonuses": {}
        }
      }
    },
    "fey": {
      "hd": 6,
      "ranks": 6,
      "bab": 0.5,
      "fort": { "mult": 0.33, "bonus": 2 },
      "ref": { "mult": 0.5, "bonus": 2 },
      "will": { "mult": 0.5, "bonus": 2 },
      "skills": [ "Acrobatics", "Bluff", "Climb", "Craft", "Diplomacy", "Disguise", "Escape Artist", "Fly", "Knowledge (geography)", "Knowledge (local)", "Knowledge (nature)", "Perception", "Perform", "Sense Motive", "Sleight of Hand", "Stealth", "Swim", "Use Magic Device" ],
      "traits": {
        "Low-light Vision": {
          "trigger": "Continuous",
          "descripction": "Fey can see color in dim light.",
          "benefit": { "target": "senses", "text": "Low-Light Vision" },
          "bonuses": {}
        }
      }
    },
    "humanoid": {
      "hd": 8,
      "ranks": 2,
      "bab": 0.75,
      "fort": { "mult": 0.33, "bonus": 0 },
      "ref": { "mult": 0.33, "bonus": 0 },
      "will": { "mult": 0.33, "bonus": 0 },
      "skills": [ "Climb", "Craft", "Handle Animal", "Heal", "Profession", "Ride", "Survival" ],
      "traits": {}
    },
    "magical beast": {
      "hd": 10,
      "ranks": 2,
      "bab": 1,
      "fort": { "mult": 0.5, "bonus": 2 },
      "ref": { "mult": 0.5, "bonus": 2 },
      "will": { "mult": 0.33, "bonus": 0 },
      "skills": [ "Acrobatics", "Climb", "Fly", "Perception", "Stealth", "Swim" ],
      "traits": {
        "Darkvision": {
          "trigger": "Continuous",
          "descripction": "Magical Beasts can see in the dark up to 60 feet.",
          "benefit": { "target": "senses", "text": "Darkvision 60 ft." },
          "bonuses": {}
        },
        "Low-light Vision": {
          "trigger": "Continuous",
          "descripction": "Magical Beasts can see color in dim light.",
          "benefit": { "target": "senses", "text": "Low-Light Vision" },
          "bonuses": {}
        }
      }
    },
    "monstrous humanoid": {
      "hd": 10,
      "ranks": 4,
      "bab": 1,
      "fort": { "mult": 0.33, "bonus": 0 },
      "ref": { "mult": 0.5, "bonus": 2 },
      "will": { "mult": 0.5, "bonus": 2 },
      "skills": [ "Climb", "Craft", "Fly", "Intimidate", "Perception", "Ride", "Stealth", "Survival", "Swim" ],
      "traits": {
        "Darkvision": {
          "trigger": "Continuous",
          "descripction": "Monstrous Humanoids can see in the dark up to 60 feet.",
          "benefit": { "target": "senses", "text": "Darkvision 60 ft." },
          "bonuses": {}
        }
      }
    },
    "ooze": {
      "hd": 8,
      "ranks": 2,
      "bab": 0.75,
      "fort": { "mult": 0.33, "bonus": 0 },
      "ref": { "mult": 0.33, "bonus": 0 },
      "will": { "mult": 0.33, "bonus": 0 },
      "skills": [],
      "traits": {
        "Blind": {
          "trigger": "Continuous",
          "description": "Oozes are blind, they have no eyes but do possess blindsight.",
          "benefit": { "target": "senses", "text": "Blindsight 60 ft." },
          "bonuses": {
            "Blind_1": {
              "bonus": -2,
              "type": "trait",
              "targets": [ "totalAC", "touchAC", "flatAC" ],
              "active": true,
              "stacks": true
            },
            "blind_2": {
              "bonus": -4,
              "type": "trait",
              "targets": [ "strChecks", "dexChecks" ],
              "active": true,
              "stacks": true
            }
          }
        },
        "Ooze Immunities": {
          "trigger": "Continuous",
          "descripction": "Oozes have no Intelligence score, giving them immunity to mind effects, they also have a number of other immunities.",
          "benefit": { "target": "immunities", "text": "critical hits, flanking, illusions, paralysis, poison, sleep, stunning, mind effects, polymorph, precision damage, gaze attacks, visual effects" },
          "bonuses": {}
        }
      }
    },
    "outsider": {
      "hd": 10,
      "ranks": 6,
      "bab": 1,
      "fort": { "mult": 0.33, "bonus": 0 },
      "ref": { "mult": 0.33, "bonus": 0 },
      "will": { "mult": 0.33, "bonus": 0 },
      "skills": [ "Bluff", "Craft", "Knowledge (planes)", "Perception", "Sense Motive", "Stealth" ],
      "traits": {
        "Darkvision": {
          "trigger": "Continuous",
          "descripction": "Outsiders can see in the dark up to 60 feet.",
          "benefit": { "target": "senses", "text": "Darkvision 60 ft." },
          "bonuses": {}
        }
      }
    },
    "plant": {
      "hd": 8,
      "ranks": 2,
      "bab": 0.75,
      "fort": { "mult": 0.5, "bonus": 2 },
      "ref": { "mult": 0.33, "bonus": 0 },
      "will": { "mult": 0.33, "bonus": 0 },
      "skills": [ "Perception", "Stealth" ],
      "traits": {
        "Low-light Vision": {
          "trigger": "Continuous",
          "descripction": "Plants can see color in dim light.",
          "benefit": { "target": "senses", "text": "Low-Light Vision" },
          "bonuses": {}
        },
        "Plant Immunities": {
          "trigger": "Continuous",
          "descripction": "Plants are immune to a number of afects and abilities, mostly related to poisons or mind effects.",
          "benefit": { "target": "immunities", "text": "mind effects, paralysis, poison, polymorph, sleep, stunning" },
          "bonuses": {}
        }
      }
    },
    "undead": {
      "hd": 8,
      "ranks": 4,
      "bab": 0.75,
      "fort": { "mult": 0.33, "bonus": 0 },
      "ref": { "mult": 0.33, "bonus": 0 },
      "will": { "mult": 0.5, "bonus": 2 },
      "skills": [ "Climb", "Disguise", "Fly", "Intimidate", "Knowledge (arcana)", "Knowledge (religion)", "Perception", "Sense Motive", "Spellcraft", "Stealth" ],
      "traits": {
        "Darkvision": {
          "trigger": "Continuous",
          "descripction": "Undead can see in the dark up to 60 feet.",
          "benefit": { "target": "senses", "text": "Darkvision 60 ft." },
          "bonuses": {}
        },
        "Undead Immunities": {
          "trigger": "Continuous",
          "descripction": "Undead are immune to a number of afects and abilities, mostly related to injuries the living may sustain like diseases.",
          "benefit": { "target": "immunities", "text": "nonlethal damage, mind effects, bleed, disease, sleep, paralysis, poison, stunning, exhaustion, fatigue, death effects, physical ability damage, ability drain, energy drain" },
          "bonuses": {}
        }
      }
    },
    "vermin": {
      "hd": 8,
      "ranks": 2,
      "bab": 0.75,
      "fort": { "mult": 0.5, "bonus": 2 },
      "ref": { "mult": 0.33, "bonus": 0 },
      "will": { "mult": 0.33, "bonus": 0 },
      "skills": [],
      "traits": {
        "Darkvision": {
          "trigger": "Continuous",
          "descripction": "Vermin can see in the dark up to 60 feet.",
          "benefit": { "target": "senses", "text": "Darkvision 60 ft." },
          "bonuses": {}
        },
        "Mindless": {
          "trigger": "Continuous",
          "descripction": "Vermin have no intelligence score, and immunity to all mind-affecting effects.",
          "benefit": { "targtet": "immunities", "text": "mind effects" },
          "bonuses": {}
        }
      }
    }
  },

  "skills": {
    "Acrobatics": { "untrained": true,  "armor_pen": true,  "ability": "Dex" },
    "Appraise": { "untrained": true,  "armor_pen": false,  "ability": "Int" },
    "Bluff": { "untrained": true,  "armor_pen": false,  "ability": "Cha" },
    "Climb": { "untrained": true,  "armor_pen": true,  "ability": "Str" },
    "Craft": { "untrained": true,  "armor_pen": false,  "ability": "Int" },
    "Diplomacy": { "untrained": true,  "armor_pen": false,  "ability": "Cha" },
    "Disable Device": { "untrained": false,  "armor_pen": true,  "ability": "Dex" },
    "Disguise": { "untrained": true,  "armor_pen": false,  "ability": "Cha" },
    "Escape Artist": { "untrained": true,  "armor_pen": true,  "ability": "Dex" },
    "Fly": { "untrained": true,  "armor_pen": true,  "ability": "Dex" },
    "Handle Animal": { "untrained": false,  "armor_pen": false,  "ability": "Cha" },
    "Heal": { "untrained": true,  "armor_pen": false,  "ability": "Wis" },
    "Intimidate": { "untrained": true,  "armor_pen": false,  "ability": "Cha" },
    "Knowledge (arcana)": { "untrained": false,  "armor_pen": false,  "ability": "Int" },
    "Knowledge (dungeoneering)": { "untrained": false,  "armor_pen": false,  "ability": "Int" },
    "Knowledge (engineering)": { "untrained": false,  "armor_pen": false,  "ability": "Int" },
    "Knowledge (geography)": { "untrained": false,  "armor_pen": false,  "ability": "Int" },
    "Knowledge (history)": { "untrained": false,  "armor_pen": false,  "ability": "Int" },
    "Knowledge (local)": { "untrained": false,  "armor_pen": false,  "ability": "Int" },
    "Knowledge (nature)": { "untrained": false,  "armor_pen": false,  "ability": "Int" },
    "Knowledge (nobility)": { "untrained": false,  "armor_pen": false,  "ability": "Int" },
    "Knowledge (planes)": { "untrained": false,  "armor_pen": false,  "ability": "Int" },
    "Knowledge (religion)": { "untrained": false,  "armor_pen": false,  "ability": "Int" },
    "Linguistics": { "untrained": false,  "armor_pen": false,  "ability": "Int" },
    "Perception": { "untrained": true,  "armor_pen": false,  "ability": "Wis" },
    "Perform": { "untrained": true,  "armor_pen": false,  "ability": "Cha" },
    "Profession": { "untrained": false,  "armor_pen": false,  "ability": "Wis" },
    "Ride": { "untrained": true,  "armor_pen": true,  "ability": "Dex" },
    "Sense Motive": { "untrained": true,  "armor_pen": false,  "ability": "Wis" },
    "Sleight of Hand": { "untrained": false,  "armor_pen": true,  "ability": "Dex" },
    "Spellcraft": { "untrained": false,  "armor_pen": false,  "ability": "Int" },
    "Stealth": { "untrained": true,  "armor_pen": true,  "ability": "Dex" },
    "Survival": { "untrained": true,  "armor_pen": false,  "ability": "Wis" },
    "Swim": { "untrained": true,  "armor_pen": true,  "ability": "Str" },
    "Use Magic Device": { "untrained": false,  "armor_pen": false,  "ability": "Cha" }
  }


}
